README.md
setup.py
GBGE_distributions/Binomialdistribution.py
GBGE_distributions/Gaussiandistribution.py
GBGE_distributions/Generaldistribution.py
GBGE_distributions/__init__.py
GBGE_distributions.egg-info/PKG-INFO
GBGE_distributions.egg-info/SOURCES.txt
GBGE_distributions.egg-info/dependency_links.txt
GBGE_distributions.egg-info/not-zip-safe
GBGE_distributions.egg-info/top_level.txt