Metadata-Version: 1.0
Name: GBGE-distributions
Version: 0.1
Summary: Gaussian_Binomial_General_distributions
Home-page: UNKNOWN
Author: Nishrin Kachwala
Author-email: nishrin.kachwala1@gmail.com
License: UNKNOWN
Platform: UNKNOWN
